{
  "v": "0",
  "id": "04441815-55b8-48b6-909e-b9de67a080b7",
  "rev": 1,
  "name": "Watchguard Content Pack_apply third ",
  "summary": "[auto-generated]",
  "description": "Watchguard logs parsed by Graylog - Input and Extractors",
  "vendor": "[auto-generated]",
  "url": "https://www.graylog.org/",
  "parameters": [],
  "entities": [
    {
      "v": "1",
      "type": {
        "name": "grok_pattern",
        "version": "1"
      },
      "id": "dff4f45f-8aae-4357-8eb5-0af26c5dd05e",
      "data": {
        "name": "NOTSPACE",
        "pattern": "\\S+"
      },
      "constraints": [
        {
          "type": "server-version",
          "version": ">=3.0.2+1686930"
        }
      ]
    },
    {
      "v": "1",
      "type": {
        "name": "grok_pattern",
        "version": "1"
      },
      "id": "faf57bf5-3260-411b-a71c-b906d94e770c",
      "data": {
        "name": "DATA",
        "pattern": ".*?"
      },
      "constraints": [
        {
          "type": "server-version",
          "version": ">=3.0.2+1686930"
        }
      ]
    },
    {
      "v": "1",
      "type": {
        "name": "grok_pattern",
        "version": "1"
      },
      "id": "1555e22f-4108-4925-b423-2b07b566544c",
      "data": {
        "name": "IPV4",
        "pattern": "(?<![0-9])(?:(?:[0-1]?[0-9]{1,2}|2[0-4][0-9]|25[0-5])[.](?:[0-1]?[0-9]{1,2}|2[0-4][0-9]|25[0-5])[.](?:[0-1]?[0-9]{1,2}|2[0-4][0-9]|25[0-5])[.](?:[0-1]?[0-9]{1,2}|2[0-4][0-9]|25[0-5]))(?![0-9])"
      },
      "constraints": [
        {
          "type": "server-version",
          "version": ">=3.0.2+1686930"
        }
      ]
    },
    {
      "v": "1",
      "type": {
        "name": "grok_pattern",
        "version": "1"
      },
      "id": "fef01063-7710-4b94-ad48-e21dda5464da",
      "data": {
        "name": "BASE10NUM",
        "pattern": "(?<![0-9.+-])(?>[+-]?(?:(?:[0-9]+(?:\\.[0-9]+)?)|(?:\\.[0-9]+)))"
      },
      "constraints": [
        {
          "type": "server-version",
          "version": ">=3.0.2+1686930"
        }
      ]
    },
    {
      "v": "1",
      "type": {
        "name": "grok_pattern",
        "version": "1"
      },
      "id": "32f510f0-b5d3-4a4b-af65-505f5a2f03fa",
      "data": {
        "name": "SECOND",
        "pattern": "(?:(?:[0-5]?[0-9]|60)(?:[:.,][0-9]+)?)"
      },
      "constraints": [
        {
          "type": "server-version",
          "version": ">=3.0.2+1686930"
        }
      ]
    },
    {
      "v": "1",
      "type": {
        "name": "grok_pattern",
        "version": "1"
      },
      "id": "23596cab-19ce-4a7b-a7dc-24266cd4f142",
      "data": {
        "name": "DHCPMESSAGE",
        "pattern": "(DHCPDISCOVER|DHCPOFFER|DHCPREQUEST|DHCPACK|DHCPNAK|DHCPRELEASE|DHCPDECLINE)"
      },
      "constraints": [
        {
          "type": "server-version",
          "version": ">=3.0.2+1686930"
        }
      ]
    },
    {
      "v": "1",
      "type": {
        "name": "grok_pattern",
        "version": "1"
      },
      "id": "1d06df87-be5b-465c-b15d-b6b59471e28e",
      "data": {
        "name": "COMMONMAC",
        "pattern": "(?:(?:[A-Fa-f0-9]{2}:){5}[A-Fa-f0-9]{2})"
      },
      "constraints": [
        {
          "type": "server-version",
          "version": ">=3.0.2+1686930"
        }
      ]
    },
    {
      "v": "1",
      "type": {
        "name": "grok_pattern",
        "version": "1"
      },
      "id": "5993d929-a38e-4c0f-a797-74ffdc5b1767",
      "data": {
        "name": "MAC",
        "pattern": "(?:%{CISCOMAC}|%{WINDOWSMAC}|%{COMMONMAC})"
      },
      "constraints": [
        {
          "type": "server-version",
          "version": ">=3.0.2+1686930"
        }
      ]
    },
    {
      "v": "1",
      "type": {
        "name": "grok_pattern",
        "version": "1"
      },
      "id": "55d245e8-bae9-40b3-99da-259ad2f503d7",
      "data": {
        "name": "NUMBER",
        "pattern": "(?:%{BASE10NUM})"
      },
      "constraints": [
        {
          "type": "server-version",
          "version": ">=3.0.2+1686930"
        }
      ]
    },
    {
      "v": "1",
      "type": {
        "name": "grok_pattern",
        "version": "1"
      },
      "id": "f8390bf8-2f9b-4521-ab77-c9d218fbbec1",
      "data": {
        "name": "WINDOWSMAC",
        "pattern": "(?:(?:[A-Fa-f0-9]{2}-){5}[A-Fa-f0-9]{2})"
      },
      "constraints": [
        {
          "type": "server-version",
          "version": ">=3.0.2+1686930"
        }
      ]
    },
    {
      "v": "1",
      "type": {
        "name": "grok_pattern",
        "version": "1"
      },
      "id": "01f679dc-93c2-4e04-9ae0-87745e83a313",
      "data": {
        "name": "CISCOMAC",
        "pattern": "(?:(?:[A-Fa-f0-9]{4}\\.){2}[A-Fa-f0-9]{4})"
      },
      "constraints": [
        {
          "type": "server-version",
          "version": ">=3.0.2+1686930"
        }
      ]
    },
    {
      "v": "1",
      "type": {
        "name": "input",
        "version": "1"
      },
      "id": "c9dbfa4a-baed-4752-8c58-18ffcbaae9cd",
      "data": {
        "title": {
          "@type": "string",
          "@value": "watchguard-syslog-udp"
        },
        "configuration": {
          "expand_structured_data": {
            "@type": "boolean",
            "@value": false
          },
          "recv_buffer_size": {
            "@type": "integer",
            "@value": 262144
          },
          "port": {
            "@type": "integer",
            "@value": 55514
          },
          "number_worker_threads": {
            "@type": "integer",
            "@value": 4
          },
          "force_rdns": {
            "@type": "boolean",
            "@value": false
          },
          "allow_override_date": {
            "@type": "boolean",
            "@value": true
          },
          "bind_address": {
            "@type": "string",
            "@value": "0.0.0.0"
          },
          "store_full_message": {
            "@type": "boolean",
            "@value": false
          }
        },
        "static_fields": {
          "from_syslog": {
            "@type": "string",
            "@value": "true"
          },
          "device": {
            "@type": "string",
            "@value": "watchguard"
          }
        },
        "type": {
          "@type": "string",
          "@value": "org.graylog2.inputs.syslog.udp.SyslogUDPInput"
        },
        "global": {
          "@type": "boolean",
          "@value": false
        },
        "extractors": [
          {
            "target_field": {
              "@type": "string",
              "@value": "msg_id"
            },
            "condition_value": {
              "@type": "string",
              "@value": "^.*: msg_id.*"
            },
            "order": {
              "@type": "integer",
              "@value": 0
            },
            "converters": [],
            "configuration": {
              "regex_value": {
                "@type": "string",
                "@value": "^.*msg_id=\\\"(\\S\\S\\S\\S-\\S\\S\\S\\S)\\\""
              }
            },
            "source_field": {
              "@type": "string",
              "@value": "message"
            },
            "title": {
              "@type": "string",
              "@value": "Message ID"
            },
            "type": {
              "@type": "string",
              "@value": "REGEX"
            },
            "cursor_strategy": {
              "@type": "string",
              "@value": "COPY"
            },
            "condition_type": {
              "@type": "string",
              "@value": "REGEX"
            }
          },
          {
            "target_field": {
              "@type": "string",
              "@value": "policy_name"
            },
            "condition_value": {
              "@type": "string",
              "@value": "^.*tcp|udp|icmp.*\\((.*)-\\d\\d\\)"
            },
            "order": {
              "@type": "integer",
              "@value": 4
            },
            "converters": [],
            "configuration": {
              "regex_value": {
                "@type": "string",
                "@value": "^.*\\((.*)-\\d\\d\\)"
              }
            },
            "source_field": {
              "@type": "string",
              "@value": "message"
            },
            "title": {
              "@type": "string",
              "@value": "Name of Firewall Policy"
            },
            "type": {
              "@type": "string",
              "@value": "REGEX"
            },
            "cursor_strategy": {
              "@type": "string",
              "@value": "COPY"
            },
            "condition_type": {
              "@type": "string",
              "@value": "REGEX"
            }
          },
          {
            "target_field": {
              "@type": "string",
              "@value": "msg_level"
            },
            "condition_value": {
              "@type": "string",
              "@value": ""
            },
            "order": {
              "@type": "integer",
              "@value": 2
            },
            "converters": [],
            "configuration": {
              "lookup_table_name": {
                "@type": "string",
                "@value": "looklookup-table-fireware-msg-id-to-level"
              }
            },
            "source_field": {
              "@type": "string",
              "@value": "msg_id"
            },
            "title": {
              "@type": "string",
              "@value": "Fireware Message Level"
            },
            "type": {
              "@type": "string",
              "@value": "LOOKUP_TABLE"
            },
            "cursor_strategy": {
              "@type": "string",
              "@value": "COPY"
            },
            "condition_type": {
              "@type": "string",
              "@value": "NONE"
            }
          },
          {
            "target_field": {
              "@type": "string",
              "@value": "msg_area"
            },
            "condition_value": {
              "@type": "string",
              "@value": ""
            },
            "order": {
              "@type": "integer",
              "@value": 3
            },
            "converters": [],
            "configuration": {
              "lookup_table_name": {
                "@type": "string",
                "@value": "lookup-table-fireware-msg-id-to-area"
              }
            },
            "source_field": {
              "@type": "string",
              "@value": "msg_id"
            },
            "title": {
              "@type": "string",
              "@value": "Fireware Message Area"
            },
            "type": {
              "@type": "string",
              "@value": "LOOKUP_TABLE"
            },
            "cursor_strategy": {
              "@type": "string",
              "@value": "COPY"
            },
            "condition_type": {
              "@type": "string",
              "@value": "NONE"
            }
          },
          {
            "target_field": {
              "@type": "string",
              "@value": "msg_name"
            },
            "condition_value": {
              "@type": "string",
              "@value": ""
            },
            "order": {
              "@type": "integer",
              "@value": 5
            },
            "converters": [],
            "configuration": {
              "lookup_table_name": {
                "@type": "string",
                "@value": "lookup-table-fireware-msg-id-to-name"
              }
            },
            "source_field": {
              "@type": "string",
              "@value": "msg_id"
            },
            "title": {
              "@type": "string",
              "@value": "Fireware Message Name"
            },
            "type": {
              "@type": "string",
              "@value": "LOOKUP_TABLE"
            },
            "cursor_strategy": {
              "@type": "string",
              "@value": "COPY"
            },
            "condition_type": {
              "@type": "string",
              "@value": "NONE"
            }
          },
          {
            "target_field": {
              "@type": "string",
              "@value": "msg_desc"
            },
            "condition_value": {
              "@type": "string",
              "@value": ""
            },
            "order": {
              "@type": "integer",
              "@value": 6
            },
            "converters": [],
            "configuration": {
              "lookup_table_name": {
                "@type": "string",
                "@value": "lookup-table-fireware-msg-id-to-description"
              }
            },
            "source_field": {
              "@type": "string",
              "@value": "msg_id"
            },
            "title": {
              "@type": "string",
              "@value": "FIreware Message Description"
            },
            "type": {
              "@type": "string",
              "@value": "LOOKUP_TABLE"
            },
            "cursor_strategy": {
              "@type": "string",
              "@value": "COPY"
            },
            "condition_type": {
              "@type": "string",
              "@value": "NONE"
            }
          },
          {
            "target_field": {
              "@type": "string",
              "@value": "policy_name"
            },
            "condition_value": {
              "@type": "string",
              "@value": "^.*tcp|udp|icmp.*\\((.*)\\)$"
            },
            "order": {
              "@type": "integer",
              "@value": 1
            },
            "converters": [],
            "configuration": {
              "regex_value": {
                "@type": "string",
                "@value": "^.*\\((.*)\\)$"
              }
            },
            "source_field": {
              "@type": "string",
              "@value": "message"
            },
            "title": {
              "@type": "string",
              "@value": "Name of Firewall Policy - Internal"
            },
            "type": {
              "@type": "string",
              "@value": "REGEX"
            },
            "cursor_strategy": {
              "@type": "string",
              "@value": "COPY"
            },
            "condition_type": {
              "@type": "string",
              "@value": "REGEX"
            }
          },
          {
            "target_field": {
              "@type": "string",
              "@value": ""
            },
            "condition_value": {
              "@type": "string",
              "@value": "^.*msg_id=\\\"3000-0148\\\".*"
            },
            "order": {
              "@type": "integer",
              "@value": 8
            },
            "converters": [],
            "configuration": {
              "grok_pattern": {
                "@type": "string",
                "@value": "^.* %{NOTSPACE:action} %{NOTSPACE:srcif} %{NOTSPACE:dstif} %{BASE10NUM:ip_pkt_len} %{NOTSPACE:protocol} %{BASE10NUM:iph_len} %{BASE10NUM:TTL} (%{IPV4:srcip}|%{DATA:srcuser}) (%{IPV4:dstip}|%{DATA:dstuser}) %{BASE10NUM:srcport} %{BASE10NUM:dstport} %{DATA:ip_pkt_info} ((?:\\s+(geo_src=\\\"%{DATA:geo_src}\\\"|geo_dst=\\\"%{DATA:geo_dst}\\\")?)|\\()"
              }
            },
            "source_field": {
              "@type": "string",
              "@value": "message"
            },
            "title": {
              "@type": "string",
              "@value": "Firewall PacketFilter INFO 3000-0148"
            },
            "type": {
              "@type": "string",
              "@value": "GROK"
            },
            "cursor_strategy": {
              "@type": "string",
              "@value": "COPY"
            },
            "condition_type": {
              "@type": "string",
              "@value": "REGEX"
            }
          },
          {
            "target_field": {
              "@type": "string",
              "@value": ""
            },
            "condition_value": {
              "@type": "string",
              "@value": "^.*msg_id=\\\"1AFF-0024\\\".*"
            },
            "order": {
              "@type": "integer",
              "@value": 9
            },
            "converters": [],
            "configuration": {
              "grok_pattern": {
                "@type": "string",
                "@value": "^.* %{NOTSPACE:action} %{NOTSPACE:srcif} %{NOTSPACE:dstif} %{NOTSPACE:protocol} %{IPV4:srcip} %{IPV4:dstip} %{BASE10NUM:srcport} %{BASE10NUM:dstport} msg=\\\"%{DATA:proxy_msg}\\\" proxy_act=\\\"%{DATA:proxy_action}\\\" op=\\\"%{DATA:proxy_op}\\\" dstname=\\\"%{DATA:proxy_dstname}\\\" arg=\\\"%{DATA:proxy_arg}\\\" sent_bytes=\\\"%{BASE10NUM:sent_bytes}\\\" rcvd_bytes=\\\"%{BASE10NUM:rcvd_bytes}\\\" elapsed_time=\\\"%{SECOND:elapsed_time} sec\\(s\\)\\\"(?:\\s+(geo_dst=\\\"%{DATA:geo_dst}\\\")?)"
              }
            },
            "source_field": {
              "@type": "string",
              "@value": "message"
            },
            "title": {
              "@type": "string",
              "@value": "Proxy HTTP INFO 1AFF-0024"
            },
            "type": {
              "@type": "string",
              "@value": "GROK"
            },
            "cursor_strategy": {
              "@type": "string",
              "@value": "COPY"
            },
            "condition_type": {
              "@type": "string",
              "@value": "REGEX"
            }
          },
          {
            "target_field": {
              "@type": "string",
              "@value": ""
            },
            "condition_value": {
              "@type": "string",
              "@value": "^.*msg_id=\\\"1AFF-0033\\\".*"
            },
            "order": {
              "@type": "integer",
              "@value": 7
            },
            "converters": [],
            "configuration": {
              "grok_pattern": {
                "@type": "string",
                "@value": "^.* %{NOTSPACE:action} %{NOTSPACE:srcif} %{NOTSPACE:dstif} %{NOTSPACE:protocol} %{IPV4:srcip} %{IPV4:dstip} %{BASE10NUM:srcport} %{BASE10NUM:dstport} msg=\\\"%{DATA:proxy_msg}\\\" proxy_act=\\\"%{DATA:proxy_action}\\\" header=\\\"%{DATA:proxy_header}\\\" (?:\\s+(geo_dst=\\\"%{DATA:geo_dst}\\\")?)"
              }
            },
            "source_field": {
              "@type": "string",
              "@value": "message"
            },
            "title": {
              "@type": "string",
              "@value": "Proxy HTTP INFO 1AFF-0033"
            },
            "type": {
              "@type": "string",
              "@value": "GROK"
            },
            "cursor_strategy": {
              "@type": "string",
              "@value": "COPY"
            },
            "condition_type": {
              "@type": "string",
              "@value": "REGEX"
            }
          },
          {
            "target_field": {
              "@type": "string",
              "@value": ""
            },
            "condition_value": {
              "@type": "string",
              "@value": "^.*msg_id=\\\"2CFF-0000\\\".*"
            },
            "order": {
              "@type": "integer",
              "@value": 11
            },
            "converters": [],
            "configuration": {
              "grok_pattern": {
                "@type": "string",
                "@value": "^.* %{NOTSPACE:action} %{NOTSPACE:srcif} %{NOTSPACE:dstif} %{NOTSPACE:protocol} %{IPV4:srcip} %{IPV4:dstip} %{BASE10NUM:srcport} %{BASE10NUM:dstport} msg=\\\"%{DATA:proxy_msg}\\\" proxy_act=\\\"%{DATA:proxy_action}\\\" sni=\\\"%{DATA:sni}\\\" cn=\\\"%{DATA:cn}\\\" cert_issuer=\\\"%{DATA:cert_issuer}\\\" cert_subject=\\\"%{DATA:cert_subject}\\\" action=\\\"%{DATA:cert_action}\\\" app_id=\\\"%{DATA:app_id}\\\" app_cat_id=\\\"%{DATA:app_cat_id}\\\" sent_bytes=\\\"%{BASE10NUM:sent_bytes}\\\" rcvd_bytes=\\\"%{BASE10NUM:rcvd_bytes}\\\" (?:\\s+(geo_dst=\\\"%{DATA:geo_dst}\\\")?)"
              }
            },
            "source_field": {
              "@type": "string",
              "@value": "message"
            },
            "title": {
              "@type": "string",
              "@value": "Proxy HTTPS INFO 2CFF-0000"
            },
            "type": {
              "@type": "string",
              "@value": "GROK"
            },
            "cursor_strategy": {
              "@type": "string",
              "@value": "COPY"
            },
            "condition_type": {
              "@type": "string",
              "@value": "REGEX"
            }
          },
          {
            "target_field": {
              "@type": "string",
              "@value": ""
            },
            "condition_value": {
              "@type": "string",
              "@value": "^.*msg_id=\\\"2CFF-0008\\\".*"
            },
            "order": {
              "@type": "integer",
              "@value": 10
            },
            "converters": [],
            "configuration": {
              "grok_pattern": {
                "@type": "string",
                "@value": "^.* %{NOTSPACE:action} %{NOTSPACE:srcif} %{NOTSPACE:dstif} %{NOTSPACE:protocol} %{IPV4:srcip} %{IPV4:dstip} %{BASE10NUM:srcport} %{BASE10NUM:dstport} msg=\\\"%{DATA:proxy_msg}\\\"(?:\\s+(geo_dst=\\\"%{DATA:geo_dst}\\\")?)"
              }
            },
            "source_field": {
              "@type": "string",
              "@value": "message"
            },
            "title": {
              "@type": "string",
              "@value": "Proxy HTTPS INFO 2CFF-0008"
            },
            "type": {
              "@type": "string",
              "@value": "GROK"
            },
            "cursor_strategy": {
              "@type": "string",
              "@value": "COPY"
            },
            "condition_type": {
              "@type": "string",
              "@value": "REGEX"
            }
          },
          {
            "target_field": {
              "@type": "string",
              "@value": ""
            },
            "condition_value": {
              "@type": "string",
              "@value": "^.*msg_id=\\\"1BFF-0001\\\".*"
            },
            "order": {
              "@type": "integer",
              "@value": 12
            },
            "converters": [],
            "configuration": {
              "grok_pattern": {
                "@type": "string",
                "@value": "^.* %{NOTSPACE:action} %{NOTSPACE:srcif} %{NOTSPACE:dstif} %{NOTSPACE:protocol} %{IPV4:srcip} %{IPV4:dstip} %{BASE10NUM:srcport} %{BASE10NUM:dstport} msg=\\\"%{DATA:proxy_msg}\\\" proxy_act=\\\"%{DATA:proxy_action}\\\" keyword=\\\"%{NOTSPACE:keyword} ((?:\\s+(geo_src=\\\"%{DATA:geo_src}\\\"|geo_dst=\\\"%{DATA:geo_dst}\\\")?)|\\()"
              }
            },
            "source_field": {
              "@type": "string",
              "@value": "message"
            },
            "title": {
              "@type": "string",
              "@value": "Proxy SMTP INFO 1BFF-0001"
            },
            "type": {
              "@type": "string",
              "@value": "GROK"
            },
            "cursor_strategy": {
              "@type": "string",
              "@value": "COPY"
            },
            "condition_type": {
              "@type": "string",
              "@value": "REGEX"
            }
          },
          {
            "target_field": {
              "@type": "string",
              "@value": ""
            },
            "condition_value": {
              "@type": "string",
              "@value": "^.*msg_id=\\\"1BFF-000F\\\".*"
            },
            "order": {
              "@type": "integer",
              "@value": 13
            },
            "converters": [],
            "configuration": {
              "grok_pattern": {
                "@type": "string",
                "@value": "^.* %{NOTSPACE:action} %{NOTSPACE:srcif} %{NOTSPACE:dstif} %{NOTSPACE:protocol} %{IPV4:srcip} %{IPV4:dstip} %{BASE10NUM:srcport} %{BASE10NUM:dstport} msg=\\\"%{DATA:proxy_msg}\\\" proxy_act=\\\"%{DATA:proxy_action}\\\" rcvd_bytes=\\\"%{BASE10NUM:rcvd_bytes}\\\" sent_bytes=\\\"%{BASE10NUM:sent_bytes}\\\" sender=\\\"%{DATA:sender}\\\" recipients=\\\"%{DATA:recipients}\\\" server_ssl=\\\"%{DATA:server_ssl}\\\" client_ssl=\\\"%{DATA:client_ssl}\\\" ((?:\\\\s+(geo_src=\\\"%{DATA:geo_src}\\\"|geo_dst=\\\"%{DATA:geo_dst}\\\")?)|\\() "
              }
            },
            "source_field": {
              "@type": "string",
              "@value": "message"
            },
            "title": {
              "@type": "string",
              "@value": "Proxy SMTP INFO 1BFF-000F"
            },
            "type": {
              "@type": "string",
              "@value": "GROK"
            },
            "cursor_strategy": {
              "@type": "string",
              "@value": "COPY"
            },
            "condition_type": {
              "@type": "string",
              "@value": "REGEX"
            }
          },
          {
            "target_field": {
              "@type": "string",
              "@value": ""
            },
            "condition_value": {
              "@type": "string",
              "@value": "^.*msg_id=\\\"1600-0065\\\".*"
            },
            "order": {
              "@type": "integer",
              "@value": 14
            },
            "converters": [],
            "configuration": {
              "grok_pattern": {
                "@type": "string",
                "@value": "^.*\\) %{NOTSPACE:service}\\[%{NOTSPACE:process}\\]: msg_id=\\\"1600-0065\\\" %{DHCPMESSAGE:dhcp_message} (on|to) %{IPV4:dhcp_clientip}( to %{MAC:dhcp_clientmac} \\(%{NOTSPACE:dhcp_clientname}\\) via| \\(%{COMMONMAC:dhcp_clientmac}\\) via) vlan%{NOTSPACE:dhcp_clientvlan}"
              }
            },
            "source_field": {
              "@type": "string",
              "@value": "message"
            },
            "title": {
              "@type": "string",
              "@value": "Networking DHCP INFO 1600-0065"
            },
            "type": {
              "@type": "string",
              "@value": "GROK"
            },
            "cursor_strategy": {
              "@type": "string",
              "@value": "COPY"
            },
            "condition_type": {
              "@type": "string",
              "@value": "REGEX"
            }
          },
          {
            "target_field": {
              "@type": "string",
              "@value": ""
            },
            "condition_value": {
              "@type": "string",
              "@value": "^.*msg_id=\\\"1600-0066\\\".*"
            },
            "order": {
              "@type": "integer",
              "@value": 15
            },
            "converters": [],
            "configuration": {
              "grok_pattern": {
                "@type": "string",
                "@value": "^.*\\) %{NOTSPACE:service}\\[%{NOTSPACE:process}\\]: msg_id=\\\"1600-0066\\\" %{DHCPMESSAGE:dhcp_message} (from|(for %{IPV4:dhcp_clientip}|for %{IPV4:dhcp_clientip} \\(%{IPV4:dhcp_serverip}\\)) from) %{MAC:dhcp_clientmac} (via|\\(%{NOTSPACE:dhcp_clientname}\\) via) vlan%{NUMBER:dhcp_clientvlan}"
              }
            },
            "source_field": {
              "@type": "string",
              "@value": "message"
            },
            "title": {
              "@type": "string",
              "@value": "Networking DHCP INFO 1600-0066"
            },
            "type": {
              "@type": "string",
              "@value": "GROK"
            },
            "cursor_strategy": {
              "@type": "string",
              "@value": "COPY"
            },
            "condition_type": {
              "@type": "string",
              "@value": "REGEX"
            }
          },
          {
            "target_field": {
              "@type": "string",
              "@value": "geo_src_coords"
            },
            "condition_value": {
              "@type": "string",
              "@value": ""
            },
            "order": {
              "@type": "integer",
              "@value": 17
            },
            "converters": [],
            "configuration": {
              "lookup_table_name": {
                "@type": "string",
                "@value": "Countrycode3_to_latlong"
              }
            },
            "source_field": {
              "@type": "string",
              "@value": "geo_src"
            },
            "title": {
              "@type": "string",
              "@value": "geo_src to Coordinates"
            },
            "type": {
              "@type": "string",
              "@value": "LOOKUP_TABLE"
            },
            "cursor_strategy": {
              "@type": "string",
              "@value": "COPY"
            },
            "condition_type": {
              "@type": "string",
              "@value": "NONE"
            }
          },
          {
            "target_field": {
              "@type": "string",
              "@value": "geo_dst_coords"
            },
            "condition_value": {
              "@type": "string",
              "@value": ""
            },
            "order": {
              "@type": "integer",
              "@value": 16
            },
            "converters": [],
            "configuration": {
              "lookup_table_name": {
                "@type": "string",
                "@value": "Countrycode3_to_latlong"
              }
            },
            "source_field": {
              "@type": "string",
              "@value": "geo_dst"
            },
            "title": {
              "@type": "string",
              "@value": "geo_dst to Coordinates"
            },
            "type": {
              "@type": "string",
              "@value": "LOOKUP_TABLE"
            },
            "cursor_strategy": {
              "@type": "string",
              "@value": "COPY"
            },
            "condition_type": {
              "@type": "string",
              "@value": "NONE"
            }
          }
        ]
      },
      "constraints": [
        {
          "type": "server-version",
          "version": ">=3.0.2+1686930"
        }
      ]
    },
    {
      "v": "1",
      "type": {
        "name": "lookup_adapter",
        "version": "1"
      },
      "id": "c599888b-9528-4cd9-acbe-4937e80b9453",
      "data": {
        "name": {
          "@type": "string",
          "@value": "fireware-msg-id-to-level-lookup"
        },
        "title": {
          "@type": "string",
          "@value": "Fireware msg ID to Level Lookup"
        },
        "description": {
          "@type": "string",
          "@value": "Lookup Table for Watchguard msg ID's - http://www.watchguard.com/help/docs/fireware/11/en-US/log_catalog/index.html"
        },
        "configuration": {
          "type": {
            "@type": "string",
            "@value": "csvfile"
          },
          "path": {
            "@type": "string",
            "@value": "/etc/graylog/fireware_msg_id_lookup_table.csv"
          },
          "separator": {
            "@type": "string",
            "@value": ","
          },
          "quotechar": {
            "@type": "string",
            "@value": "\""
          },
          "key_column": {
            "@type": "string",
            "@value": "msg_id"
          },
          "value_column": {
            "@type": "string",
            "@value": "msg_level"
          },
          "check_interval": {
            "@type": "long",
            "@value": 180
          },
          "case_insensitive_lookup": {
            "@type": "boolean",
            "@value": false
          }
        }
      },
      "constraints": [
        {
          "type": "server-version",
          "version": ">=3.0.2+1686930"
        }
      ]
    },
    {
      "v": "1",
      "type": {
        "name": "lookup_adapter",
        "version": "1"
      },
      "id": "14b82ccf-cbda-4ea3-ae15-f7b4d4637f13",
      "data": {
        "name": {
          "@type": "string",
          "@value": "fireware-msg-id-to-area-lookup"
        },
        "title": {
          "@type": "string",
          "@value": "Fireware msg ID to Area Lookup"
        },
        "description": {
          "@type": "string",
          "@value": "Lookup Table for Watchguard msg ID's - http://www.watchguard.com/help/docs/fireware/11/en-US/log_catalog/index.html"
        },
        "configuration": {
          "type": {
            "@type": "string",
            "@value": "csvfile"
          },
          "path": {
            "@type": "string",
            "@value": "/etc/graylog/fireware_msg_id_lookup_table.csv"
          },
          "separator": {
            "@type": "string",
            "@value": ","
          },
          "quotechar": {
            "@type": "string",
            "@value": "\""
          },
          "key_column": {
            "@type": "string",
            "@value": "msg_id"
          },
          "value_column": {
            "@type": "string",
            "@value": "msg_area"
          },
          "check_interval": {
            "@type": "long",
            "@value": 18
          },
          "case_insensitive_lookup": {
            "@type": "boolean",
            "@value": false
          }
        }
      },
      "constraints": [
        {
          "type": "server-version",
          "version": ">=3.0.2+1686930"
        }
      ]
    },
    {
      "v": "1",
      "type": {
        "name": "lookup_adapter",
        "version": "1"
      },
      "id": "6a823c97-5e0d-40f6-9ec2-452fbd132630",
      "data": {
        "name": {
          "@type": "string",
          "@value": "fireware-msg-id-to-name-lookup"
        },
        "title": {
          "@type": "string",
          "@value": "Fireware msg ID to Name Lookup"
        },
        "description": {
          "@type": "string",
          "@value": "Lookup Table for Watchguard msg ID's - http://www.watchguard.com/help/docs/fireware/11/en-US/log_catalog/index.html"
        },
        "configuration": {
          "type": {
            "@type": "string",
            "@value": "csvfile"
          },
          "path": {
            "@type": "string",
            "@value": "/etc/graylog/fireware_msg_id_lookup_table.csv"
          },
          "separator": {
            "@type": "string",
            "@value": ","
          },
          "quotechar": {
            "@type": "string",
            "@value": "\""
          },
          "key_column": {
            "@type": "string",
            "@value": "msg_id"
          },
          "value_column": {
            "@type": "string",
            "@value": "msg_name"
          },
          "check_interval": {
            "@type": "long",
            "@value": 180
          },
          "case_insensitive_lookup": {
            "@type": "boolean",
            "@value": false
          }
        }
      },
      "constraints": [
        {
          "type": "server-version",
          "version": ">=3.0.2+1686930"
        }
      ]
    },
    {
      "v": "1",
      "type": {
        "name": "lookup_adapter",
        "version": "1"
      },
      "id": "1774f7c8-7d25-4920-98f0-444f3ecf691a",
      "data": {
        "name": {
          "@type": "string",
          "@value": "fireware-msg-id-to-description-lookup"
        },
        "title": {
          "@type": "string",
          "@value": "Fireware msg ID to Description Lookup"
        },
        "description": {
          "@type": "string",
          "@value": "Lookup Table for Watchguard msg ID's - http://www.watchguard.com/help/docs/fireware/11/en-US/log_catalog/index.html"
        },
        "configuration": {
          "type": {
            "@type": "string",
            "@value": "csvfile"
          },
          "path": {
            "@type": "string",
            "@value": "/etc/graylog/fireware_msg_id_lookup_table.csv"
          },
          "separator": {
            "@type": "string",
            "@value": ","
          },
          "quotechar": {
            "@type": "string",
            "@value": "\""
          },
          "key_column": {
            "@type": "string",
            "@value": "msg_id"
          },
          "value_column": {
            "@type": "string",
            "@value": "msg_desc"
          },
          "check_interval": {
            "@type": "long",
            "@value": 180
          },
          "case_insensitive_lookup": {
            "@type": "boolean",
            "@value": false
          }
        }
      },
      "constraints": [
        {
          "type": "server-version",
          "version": ">=3.0.2+1686930"
        }
      ]
    },
    {
      "v": "1",
      "type": {
        "name": "lookup_adapter",
        "version": "1"
      },
      "id": "0f2f94b2-6bc7-47f5-bc47-535106e53701",
      "data": {
        "name": {
          "@type": "string",
          "@value": "countrycode-3dig-to-latlong"
        },
        "title": {
          "@type": "string",
          "@value": "Fireware countrycode 3dig to latlong"
        },
        "description": {
          "@type": "string",
          "@value": "Lookup the countrycode table to convert 3 digit country code(UN) to 2digit country code(ISO)"
        },
        "configuration": {
          "type": {
            "@type": "string",
            "@value": "csvfile"
          },
          "path": {
            "@type": "string",
            "@value": "/etc/graylog/countrycode_lookup_table.csv"
          },
          "separator": {
            "@type": "string",
            "@value": ";"
          },
          "quotechar": {
            "@type": "string",
            "@value": "'"
          },
          "key_column": {
            "@type": "string",
            "@value": "ccode_un_a3"
          },
          "value_column": {
            "@type": "string",
            "@value": "ccode_latlong"
          },
          "check_interval": {
            "@type": "long",
            "@value": 600
          },
          "case_insensitive_lookup": {
            "@type": "boolean",
            "@value": false
          }
        }
      },
      "constraints": [
        {
          "type": "server-version",
          "version": ">=3.0.2+1686930"
        }
      ]
    },
    {
      "v": "1",
      "type": {
        "name": "lookup_cache",
        "version": "1"
      },
      "id": "968585f1-35ce-4c63-abd2-6e3510f8dee2",
      "data": {
        "name": {
          "@type": "string",
          "@value": "fireware-msg_id-cache"
        },
        "title": {
          "@type": "string",
          "@value": "Fireware msg_ID Cache"
        },
        "description": {
          "@type": "string",
          "@value": "Cache for csv Lookup of Fireware msg_id's"
        },
        "configuration": {
          "type": {
            "@type": "string",
            "@value": "guava_cache"
          },
          "max_size": {
            "@type": "integer",
            "@value": 50
          },
          "expire_after_access": {
            "@type": "long",
            "@value": 60
          },
          "expire_after_access_unit": {
            "@type": "string",
            "@value": "SECONDS"
          },
          "expire_after_write": {
            "@type": "long",
            "@value": 0
          },
          "expire_after_write_unit": {
            "@type": "string",
            "@value": "SECONDS"
          }
        }
      },
      "constraints": [
        {
          "type": "server-version",
          "version": ">=3.0.2+1686930"
        }
      ]
    },
    {
      "v": "1",
      "type": {
        "name": "lookup_cache",
        "version": "1"
      },
      "id": "0dcaa269-9ad0-423f-9071-d404ee073095",
      "data": {
        "name": {
          "@type": "string",
          "@value": "country-code-table"
        },
        "title": {
          "@type": "string",
          "@value": "Country Code Table"
        },
        "description": {
          "@type": "string",
          "@value": "Table of country codes"
        },
        "configuration": {
          "type": {
            "@type": "string",
            "@value": "guava_cache"
          },
          "max_size": {
            "@type": "integer",
            "@value": 1000
          },
          "expire_after_access": {
            "@type": "long",
            "@value": 600
          },
          "expire_after_access_unit": {
            "@type": "string",
            "@value": "SECONDS"
          },
          "expire_after_write": {
            "@type": "long",
            "@value": 0
          }
        }
      },
      "constraints": [
        {
          "type": "server-version",
          "version": ">=3.0.2+1686930"
        }
      ]
    },
    {
      "v": "1",
      "type": {
        "name": "lookup_table",
        "version": "1"
      },
      "id": "6731bdf1-7a9a-49e4-a862-fcbc656ed811",
      "data": {
        "default_single_value_type": {
          "@type": "string",
          "@value": "NULL"
        },
        "cache_name": {
          "@type": "string",
          "@value": "968585f1-35ce-4c63-abd2-6e3510f8dee2"
        },
        "name": {
          "@type": "string",
          "@value": "looklookup-table-fireware-msg-id-to-level"
        },
        "default_multi_value_type": {
          "@type": "string",
          "@value": "NULL"
        },
        "default_multi_value": {
          "@type": "string",
          "@value": ""
        },
        "data_adapter_name": {
          "@type": "string",
          "@value": "c599888b-9528-4cd9-acbe-4937e80b9453"
        },
        "title": {
          "@type": "string",
          "@value": "Lookup Table Fireware msg ID to Level"
        },
        "default_single_value": {
          "@type": "string",
          "@value": ""
        },
        "description": {
          "@type": "string",
          "@value": "Lookup Table for Watchguard msg ID's - http://www.watchguard.com/help/docs/fireware/11/en-US/log_catalog/index.html"
        }
      },
      "constraints": [
        {
          "type": "server-version",
          "version": ">=3.0.2+1686930"
        }
      ]
    },
    {
      "v": "1",
      "type": {
        "name": "lookup_table",
        "version": "1"
      },
      "id": "ede3a00a-c323-4a28-bfb8-c23c76e65a9d",
      "data": {
        "default_single_value_type": {
          "@type": "string",
          "@value": "NULL"
        },
        "cache_name": {
          "@type": "string",
          "@value": "968585f1-35ce-4c63-abd2-6e3510f8dee2"
        },
        "name": {
          "@type": "string",
          "@value": "lookup-table-fireware-msg-id-to-area"
        },
        "default_multi_value_type": {
          "@type": "string",
          "@value": "NULL"
        },
        "default_multi_value": {
          "@type": "string",
          "@value": ""
        },
        "data_adapter_name": {
          "@type": "string",
          "@value": "14b82ccf-cbda-4ea3-ae15-f7b4d4637f13"
        },
        "title": {
          "@type": "string",
          "@value": "Lookup Table Fireware msg ID to Area"
        },
        "default_single_value": {
          "@type": "string",
          "@value": ""
        },
        "description": {
          "@type": "string",
          "@value": "Lookup Table for Watchguard msg ID's - http://www.watchguard.com/help/docs/fireware/11/en-US/log_catalog/index.html"
        }
      },
      "constraints": [
        {
          "type": "server-version",
          "version": ">=3.0.2+1686930"
        }
      ]
    },
    {
      "v": "1",
      "type": {
        "name": "lookup_table",
        "version": "1"
      },
      "id": "49c83694-d05e-425a-a00d-5ce5b13542bb",
      "data": {
        "default_single_value_type": {
          "@type": "string",
          "@value": "NULL"
        },
        "cache_name": {
          "@type": "string",
          "@value": "968585f1-35ce-4c63-abd2-6e3510f8dee2"
        },
        "name": {
          "@type": "string",
          "@value": "lookup-table-fireware-msg-id-to-name"
        },
        "default_multi_value_type": {
          "@type": "string",
          "@value": "NULL"
        },
        "default_multi_value": {
          "@type": "string",
          "@value": ""
        },
        "data_adapter_name": {
          "@type": "string",
          "@value": "6a823c97-5e0d-40f6-9ec2-452fbd132630"
        },
        "title": {
          "@type": "string",
          "@value": "Lookup Table Fireware msg ID to Name"
        },
        "default_single_value": {
          "@type": "string",
          "@value": ""
        },
        "description": {
          "@type": "string",
          "@value": "Lookup Table for Watchguard msg ID's - http://www.watchguard.com/help/docs/fireware/11/en-US/log_catalog/index.html"
        }
      },
      "constraints": [
        {
          "type": "server-version",
          "version": ">=3.0.2+1686930"
        }
      ]
    },
    {
      "v": "1",
      "type": {
        "name": "lookup_table",
        "version": "1"
      },
      "id": "fe83a1bd-ac12-411b-9265-4e794ef5caf2",
      "data": {
        "default_single_value_type": {
          "@type": "string",
          "@value": "NULL"
        },
        "cache_name": {
          "@type": "string",
          "@value": "968585f1-35ce-4c63-abd2-6e3510f8dee2"
        },
        "name": {
          "@type": "string",
          "@value": "lookup-table-fireware-msg-id-to-description"
        },
        "default_multi_value_type": {
          "@type": "string",
          "@value": "NULL"
        },
        "default_multi_value": {
          "@type": "string",
          "@value": ""
        },
        "data_adapter_name": {
          "@type": "string",
          "@value": "1774f7c8-7d25-4920-98f0-444f3ecf691a"
        },
        "title": {
          "@type": "string",
          "@value": "Lookup Table Fireware msg ID to Description"
        },
        "default_single_value": {
          "@type": "string",
          "@value": ""
        },
        "description": {
          "@type": "string",
          "@value": "Lookup Table for Watchguard msg ID's - http://www.watchguard.com/help/docs/fireware/11/en-US/log_catalog/index.html"
        }
      },
      "constraints": [
        {
          "type": "server-version",
          "version": ">=3.0.2+1686930"
        }
      ]
    },
    {
      "v": "1",
      "type": {
        "name": "lookup_table",
        "version": "1"
      },
      "id": "6b0ec590-ea13-4136-98e7-b049b03f3515",
      "data": {
        "default_single_value_type": {
          "@type": "string",
          "@value": "NULL"
        },
        "cache_name": {
          "@type": "string",
          "@value": "0dcaa269-9ad0-423f-9071-d404ee073095"
        },
        "name": {
          "@type": "string",
          "@value": "Countrycode3_to_latlong"
        },
        "default_multi_value_type": {
          "@type": "string",
          "@value": "NULL"
        },
        "default_multi_value": {
          "@type": "string",
          "@value": ""
        },
        "data_adapter_name": {
          "@type": "string",
          "@value": "0f2f94b2-6bc7-47f5-bc47-535106e53701"
        },
        "title": {
          "@type": "string",
          "@value": "Countrycode3_to_latlong"
        },
        "default_single_value": {
          "@type": "string",
          "@value": ""
        },
        "description": {
          "@type": "string",
          "@value": "Use Lookuptable to convert the UN Code to latitude and longitude"
        }
      },
      "constraints": [
        {
          "type": "server-version",
          "version": ">=3.0.2+1686930"
        }
      ]
    }
  ]
}
